AH_Translit_Bench/__init__.py
AH_Translit_Bench/loader.py
AH_Translit_Bench/data/all_domain_mix_benchmark_6000.csv
AH_Translit_Bench/data/msa_bibliographic_benchmark_2000.csv
AH_Translit_Bench/data/msa_dailyuse_benchmark_2000.csv
AH_Translit_Bench/data/quranic_benchmark_2000.csv
ah_translit_bench-2.1.1.dist-info/licenses/LICENSE
ah_translit_bench-2.1.1.dist-info/METADATA
ah_translit_bench-2.1.1.dist-info/WHEEL
ah_translit_bench-2.1.1.dist-info/top_level.txt
ah_translit_bench-2.1.1.dist-info/RECORD
