Metadata-Version: 2.4
Name: AH-Translit-Bench
Version: 2.1.1
Summary: Arabic to Hindi transliteration benchmark dataset (2k per domain)
License-File: LICENSE
Dynamic: license-file
